extracta/__init__.py
extracta/analyzers/__init__.py
extracta/analyzers/base_analyzer.py
extracta/analyzers/citation_analyzer/__init__.py
extracta/analyzers/citation_analyzer/citation_analyzer.py
extracta/analyzers/code_analyzer/__init__.py
extracta/analyzers/conversation_analyzer/__init__.py
extracta/analyzers/conversation_analyzer/conversation_analyzer.py
extracta/analyzers/image_analyzer/__init__.py
extracta/analyzers/image_analyzer/image_analyzer.py
extracta/analyzers/reference_analyzer/__init__.py
extracta/analyzers/reference_analyzer/reference_analyzer.py
extracta/analyzers/text_analyzer/__init__.py
extracta/analyzers/text_analyzer/analyzer.py
extracta/analyzers/url_analyzer/__init__.py
extracta/analyzers/url_analyzer/url_analyzer.py
extracta/api/__init__.py
extracta/api/main.py
extracta/cli/__init__.py
extracta/cli/main.py
extracta/grading/__init__.py
extracta/grading/default_rubrics.py
extracta/grading/feedback_generator.py
extracta/grading/grading_lens/__init__.py
extracta/grading/rubric_manager/__init__.py
extracta/grading/rubric_manager/rubric_manager.py
extracta/lenses/__init__.py
extracta/lenses/base_lens.py
extracta/lenses/ocr_detector.py
extracta/lenses/ai_conversation_lens/__init__.py
extracta/lenses/ai_conversation_lens/ai_conversation_lens.py
extracta/lenses/audio_lens/__init__.py
extracta/lenses/audio_lens/audio_lens.py
extracta/lenses/code_lens/__init__.py
extracta/lenses/code_lens/code_lens.py
extracta/lenses/document_lens/__init__.py
extracta/lenses/document_lens/document_lens.py
extracta/lenses/image_lens/__init__.py
extracta/lenses/image_lens/image_lens.py
extracta/lenses/presentation_lens/__init__.py
extracta/lenses/presentation_lens/presentation_lens.py
extracta/lenses/repo_lens/__init__.py
extracta/lenses/repo_lens/repo_lens.py
extracta/lenses/video_lens/__init__.py
extracta/lenses/video_lens/exceptions.py
extracta/lenses/video_lens/rubrics.py
extracta/lenses/video_lens/video_lens.py
extracta/lenses/video_lens/video_processor.py
extracta-0.2.2.dist-info/METADATA
extracta-0.2.2.dist-info/WHEEL
extracta-0.2.2.dist-info/entry_points.txt
extracta-0.2.2.dist-info/licenses/LICENSE
extracta-0.2.2.dist-info/RECORD
