Metadata-Version: 2.4
Name: extracta
Version: 0.2.2
Summary: Modular content analysis platform for research, assessment, and academic integrity checking
Author-email: Michael Borck <michael@borck.dev>
License: MIT
License-File: LICENSE
Requires-Python: >=3.10
Requires-Dist: click>=8.1.0
Requires-Dist: httpx>=0.25.0
Requires-Dist: pydantic>=2.5.0
Provides-Extra: all
Requires-Dist: anthropic>=0.7.0; extra == 'all'
Requires-Dist: ast>=3.8; extra == 'all'
Requires-Dist: fastapi>=0.104.0; extra == 'all'
Requires-Dist: faster-whisper>=1.0.0; extra == 'all'
Requires-Dist: ffmpeg-python>=0.2.0; extra == 'all'
Requires-Dist: google-generativeai>=0.3.0; extra == 'all'
Requires-Dist: librosa>=0.10.0; extra == 'all'
Requires-Dist: nltk>=3.8.0; extra == 'all'
Requires-Dist: openai>=1.0.0; extra == 'all'
Requires-Dist: opencv-python>=4.8.0; extra == 'all'
Requires-Dist: pdfplumber>=0.10.0; extra == 'all'
Requires-Dist: pillow>=10.0.0; extra == 'all'
Requires-Dist: pydantic>=2.5.0; extra == 'all'
Requires-Dist: pymupdf>=1.23.0; extra == 'all'
Requires-Dist: pypdf2>=3.0.0; extra == 'all'
Requires-Dist: pytesseract>=0.3.0; extra == 'all'
Requires-Dist: python-docx>=1.1.0; extra == 'all'
Requires-Dist: python-pptx>=0.6.0; extra == 'all'
Requires-Dist: radon>=6.0.0; extra == 'all'
Requires-Dist: ruff>=0.1.0; extra == 'all'
Requires-Dist: spacy>=3.7.0; extra == 'all'
Requires-Dist: textstat>=0.7.0; extra == 'all'
Requires-Dist: torch>=2.0.0; extra == 'all'
Requires-Dist: uvicorn[standard]>=0.24.0; extra == 'all'
Provides-Extra: api
Requires-Dist: fastapi>=0.104.0; extra == 'api'
Requires-Dist: uvicorn[standard]>=0.24.0; extra == 'api'
Provides-Extra: audio
Requires-Dist: faster-whisper>=1.0.0; extra == 'audio'
Requires-Dist: librosa>=0.10.0; extra == 'audio'
Provides-Extra: claude
Requires-Dist: anthropic>=0.7.0; extra == 'claude'
Provides-Extra: code
Requires-Dist: ast>=3.8; extra == 'code'
Requires-Dist: radon>=6.0.0; extra == 'code'
Requires-Dist: ruff>=0.1.0; extra == 'code'
Provides-Extra: conversation
Requires-Dist: google-generativeai>=0.3.0; extra == 'conversation'
Provides-Extra: dev
Requires-Dist: mypy>=1.5.0; extra == 'dev'
Requires-Dist: pytest-cov>=4.1.0; extra == 'dev'
Requires-Dist: pytest>=7.4.0; extra == 'dev'
Provides-Extra: documents
Requires-Dist: pdfplumber>=0.10.0; extra == 'documents'
Requires-Dist: pypdf2>=3.0.0; extra == 'documents'
Requires-Dist: python-docx>=1.1.0; extra == 'documents'
Provides-Extra: enhanced
Requires-Dist: nltk>=3.8.0; extra == 'enhanced'
Requires-Dist: pdfplumber>=0.10.0; extra == 'enhanced'
Requires-Dist: pymupdf>=1.23.0; extra == 'enhanced'
Requires-Dist: pypdf2>=3.0.0; extra == 'enhanced'
Requires-Dist: python-docx>=1.1.0; extra == 'enhanced'
Requires-Dist: python-pptx>=0.6.0; extra == 'enhanced'
Requires-Dist: spacy>=3.7.0; extra == 'enhanced'
Requires-Dist: textstat>=0.7.0; extra == 'enhanced'
Provides-Extra: image
Requires-Dist: pillow>=10.0.0; extra == 'image'
Requires-Dist: pytesseract>=0.3.0; extra == 'image'
Requires-Dist: torch>=2.0.0; extra == 'image'
Provides-Extra: openai
Requires-Dist: openai>=1.0.0; extra == 'openai'
Provides-Extra: openrouter
Requires-Dist: openai>=1.0.0; extra == 'openrouter'
Provides-Extra: presentations
Requires-Dist: pymupdf>=1.23.0; extra == 'presentations'
Requires-Dist: python-pptx>=0.6.0; extra == 'presentations'
Provides-Extra: text
Requires-Dist: nltk>=3.8.0; extra == 'text'
Requires-Dist: spacy>=3.7.0; extra == 'text'
Requires-Dist: textstat>=0.7.0; extra == 'text'
Provides-Extra: video
Requires-Dist: ffmpeg-python>=0.2.0; extra == 'video'
Requires-Dist: opencv-python>=4.8.0; extra == 'video'
Requires-Dist: pydantic>=2.5.0; extra == 'video'
